{"@class":"Animation","id":{"uuid":"7B7A3C43-21CD-4C41-9B17-FAEBDEDFBAC4"},"tracks":[{"@class":"SoundTrack","clips":[{"@class":"SoundClip","beginTime":0,"duration":624,"script":"SoundClipScript","behavior":{"@class":"SoundSampleBehavior","volume":0.7285068035125732,"volumeModulation":0.0,"pitch":1.0,"pitchModulation":0.0,"soundSampleId":{"uuid":"32E04607-06EF-40F2-AF20-21294F88E06F"}},"color":{"values":[0.239215686917305,0.47843137383461,0.9607843160629273]}}],"script":"SoundTrackScript","accessor":"AudioSourceAccessor","volume":1.0}]}