{"@class":"Animation","id":{"uuid":"9FA7952D-03BA-421D-AEE7-9EC9ED7B45A2"},"tracks":[{"@class":"BoolBehaviorTrack","clips":[{"@class":"BoolBehaviorClip","beginTime":0,"duration":500,"script":"BoolValueBehaviorClipScript","behavior":{"@class":"BoolDiscreteBehavior","frames":[{"@class":"BoolKeyFrame","formula":{"@class":"BoolExpressionFormula","expression":"false"},"time":0},{"@class":"BoolKeyFrame","formula":{"@class":"BoolExpressionFormula","expression":"true"},"time":500}]}}],"script":"BoolBehaviorTrackScript","accessor":"Object3DEnabledBlendAccessor"}]}