{"@class":"TimeLineScript","id":{"uuid":"60660680-DDC1-4D09-947C-D668A1DD08EE"},"name":"Animation","enableOnAwake":false,"loop":false,"jumpToFirstFrameAtEnd":false,"speed":1.0,"weight":1.0,"loopStartTime":0,"loopDuration":0,"is_imported":false,"type":"user","scripts":{"@class":"StdListRuntimeScript","list":[{"@class":"AnimationScript","id":{"uuid":"64F2646B-8555-4262-BC66-FDAE4462CF3A"},"name":"GG","enableOnAwake":false,"OwnerLink":{"@class":"BindingLink","targetId":{"uuid":"476D362A-3C85-4A30-B48E-86381762F806"}},"animation":{"uuid":"76E77B0D-79D5-4288-9B9B-704E9767FB20"},"AnimationType":"object3D","is_imported":false,"isEnabled":true},{"@class":"AnimationScript","id":{"uuid":"B386565B-59FE-4042-83D9-E29848287429"},"name":"Blood","enableOnAwake":false,"OwnerLink":{"@class":"BindingLink","targetId":{"uuid":"589E661A-938A-48D8-B669-13C5C2DB6DB8"},"targetRelativeAddress":{"@class":"NodeRelativeAddressBase","index":3,"name":"Logic_animations","subaddress":{"@class":"NodeRelativeAddressBase","index":0,"name":"Blood_Ani","subaddress":{"@class":"NodeRelativeAddressBase","index":0,"name":"Blood"}}}},"animation":{"uuid":"BB1F703D-3147-484E-9BA5-2683C7171461"},"AnimationType":"object3D","is_imported":false,"isEnabled":true},{"@class":"AnimationScript","id":{"uuid":"EFFD479F-A691-4864-AC8B-AF829F4205CF"},"name":"Blood_Ani","enableOnAwake":false,"OwnerLink":{"@class":"BindingLink","targetId":{"uuid":"DB508DB0-69DE-49A6-8F8E-FF4E7E9717DA"},"targetRelativeAddress":{"@class":"NodeRelativeAddressBase","index":3,"name":"Logic_animations","subaddress":{"@class":"NodeRelativeAddressBase","index":0,"name":"Blood_Ani"}}},"animation":{"uuid":"49BACD8D-227F-4540-A0C2-FD6747075A4B"},"AnimationType":"object3D","is_imported":false,"isEnabled":true},{"@class":"AnimationScript","id":{"uuid":"BB401A61-0619-4B19-A5A2-1700829A61BE"},"name":"Lives_decrease","enableOnAwake":false,"OwnerLink":{"@class":"BindingLink","targetId":{"uuid":"2671D540-48B0-4450-8A76-723DBDF2E496"}},"animation":{"uuid":"DE941360-BDEA-47E0-87F3-6DD15936707B"},"AnimationType":"object3D","is_imported":false,"isEnabled":true},{"@class":"AnimationScript","id":{"uuid":"F9CB4E4C-C2BA-4A85-8116-F87895FB4829"},"name":"Inserted animations","enableOnAwake":false,"OwnerLink":{"@class":"BindingLink"},"animation":{"uuid":"3878D730-FA8C-497F-B0F9-3921AC2B61DA"},"AnimationType":"timeline","is_imported":false,"isEnabled":true},{"@class":"AnimationScript","id":{"uuid":"107118B9-8AEF-4E99-962C-F41DD9F8EF92"},"name":"Master Sound","enableOnAwake":false,"OwnerLink":{"@class":"BindingLink"},"animation":{"uuid":"7B7A3C43-21CD-4C41-9B17-FAEBDEDFBAC4"},"AnimationType":"masterSound","is_imported":false,"isEnabled":true}]},"triggers":[{"@class":"CollisionTrigger","id":{"uuid":"49FBF3E5-CEA1-42E0-A1E8-33A2A44CABEF"},"ownerScriptId":{"uuid":"60660680-DDC1-4D09-947C-D668A1DD08EE"},"logicOperation":0,"resultType":0,"isInverted":false,"eventType":"in","targetBindingLink":{"@class":"BindingLink","targetId":{"uuid":"1B7B7BD3-09E5-48FF-8FFE-A42DB9D9493C"}},"zoneBindingLink":{"@class":"BindingLink","targetId":{"uuid":"A312204F-7E3F-4980-A04F-7B62841EE874"}},"allowed":false},{"@class":"GroupTrigger","id":{"uuid":"B6FB36D1-1C39-4852-ADE3-F284BDB6CC34"},"ownerScriptId":{"uuid":"60660680-DDC1-4D09-947C-D668A1DD08EE"},"logicOperation":1,"resultType":0,"isInverted":true,"triggers":[{"@class":"AnimationTrigger","id":{"uuid":"5C3B1147-6479-4CC7-B9C9-5824AA7F5F76"},"ownerScriptId":{"uuid":"60660680-DDC1-4D09-947C-D668A1DD08EE"},"logicOperation":1,"resultType":0,"isInverted":false,"event":1,"bindingLink":{"@class":"BindingLink","targetId":{"uuid":"F2ECD6D3-14C6-41C3-9D8B-CCFFDDE02A69"}}},{"@class":"AnimationTrigger","id":{"uuid":"8542F5E5-FC5D-486E-ABFA-7A223AD8A0E4"},"ownerScriptId":{"uuid":"60660680-DDC1-4D09-947C-D668A1DD08EE"},"logicOperation":0,"resultType":0,"isInverted":false,"event":3,"bindingLink":{"@class":"BindingLink","targetId":{"uuid":"F2ECD6D3-14C6-41C3-9D8B-CCFFDDE02A69"}}}]}]}