{"@class":"TimeLineScript","id":{"uuid":"826065EA-65EF-42E1-92C1-970D5875D346"},"name":"Animation","enableOnAwake":false,"loop":false,"jumpToFirstFrameAtEnd":false,"speed":1.0,"weight":1.0,"loopStartTime":0,"loopDuration":0,"is_imported":false,"type":"user","scripts":{"@class":"StdListRuntimeScript","list":[{"@class":"AnimationScript","id":{"uuid":"1D51196D-D517-46A0-8299-AA12E64D6267"},"name":"Coin1","enableOnAwake":false,"OwnerLink":{"@class":"BindingLink","targetId":{"uuid":"8A657E9A-B1AD-47C2-8FED-122C12B0FED3"},"targetRelativeAddress":{"@class":"NodeRelativeAddressBase","index":2,"name":"Coin_C","subaddress":{"@class":"NodeRelativeAddressBase","index":2,"name":"Coin1"}}},"animation":{"uuid":"9EFE1616-5F53-41F6-AF8D-794FF9C6D41C"},"AnimationType":"object3D","is_imported":false,"isEnabled":true},{"@class":"AnimationScript","id":{"uuid":"961403A2-972C-4207-9227-CC595F51A7B3"},"name":"Coin2","enableOnAwake":false,"OwnerLink":{"@class":"BindingLink","targetId":{"uuid":"B3D8269E-47F3-4004-B80D-A53891EFC334"},"targetRelativeAddress":{"@class":"NodeRelativeAddressBase","index":2,"name":"Coin_C","subaddress":{"@class":"NodeRelativeAddressBase","index":3,"name":"Coin2"}}},"animation":{"uuid":"6C38D500-3E12-4441-BF0F-47FB7E8836B7"},"AnimationType":"object3D","is_imported":false,"isEnabled":true},{"@class":"AnimationScript","id":{"uuid":"27A66826-C4B6-4211-97E9-132E89D4AFF9"},"name":"Coin3","enableOnAwake":false,"OwnerLink":{"@class":"BindingLink","targetId":{"uuid":"D21ECD1C-DED7-4422-B189-DA7E39375CE9"},"targetRelativeAddress":{"@class":"NodeRelativeAddressBase","index":2,"name":"Coin_C","subaddress":{"@class":"NodeRelativeAddressBase","index":1,"name":"Coin3"}}},"animation":{"uuid":"1E20FDB1-C019-4236-8CF9-41BB198E55E0"},"AnimationType":"object3D","is_imported":false,"isEnabled":true},{"@class":"AnimationScript","id":{"uuid":"C51D1D7D-988B-422B-A4EF-2019D30044BD"},"name":"Coin4","enableOnAwake":false,"OwnerLink":{"@class":"BindingLink","targetId":{"uuid":"4299517A-41D4-4375-8768-84F0EE96E5F5"},"targetRelativeAddress":{"@class":"NodeRelativeAddressBase","index":2,"name":"Coin_C","subaddress":{"@class":"NodeRelativeAddressBase","index":4,"name":"Coin4"}}},"animation":{"uuid":"851341CE-2C5A-47D4-8692-D0927800B66B"},"AnimationType":"object3D","is_imported":false,"isEnabled":true},{"@class":"AnimationScript","id":{"uuid":"3F14E638-0E01-4BD1-BC3C-747EBD61C3E1"},"name":"Collider","enableOnAwake":false,"OwnerLink":{"@class":"BindingLink","targetId":{"uuid":"EFF14DB0-66B7-48CC-8B63-D88EA44E8F23"},"targetRelativeAddress":{"@class":"NodeRelativeAddressBase","index":2,"name":"Coin_C","subaddress":{"@class":"NodeRelativeAddressBase","index":0,"name":"Collider"}}},"animation":{"uuid":"DA0218F8-8B58-4AE7-A81E-180F692D9D25"},"AnimationType":"object3D","is_imported":false,"isEnabled":true},{"@class":"AnimationScript","id":{"uuid":"A83B376A-8059-4703-98AE-7C79844D9ED6"},"name":"Coin","enableOnAwake":false,"OwnerLink":{"@class":"BindingLink","targetId":{"uuid":"F5BF208D-AE18-4029-AA2F-CF3D9AE71913"},"targetRelativeAddress":{"@class":"NodeRelativeAddressBase","index":2,"name":"Coin_C"}},"animation":{"uuid":"0686EFC4-7B09-4850-971A-EA8693432D38"},"AnimationType":"object3D","is_imported":false,"isEnabled":true},{"@class":"AnimationScript","id":{"uuid":"945E1271-1CB3-4776-A536-C6E341793849"},"name":"Master Sound","enableOnAwake":false,"OwnerLink":{"@class":"BindingLink"},"animation":{"uuid":"705082CC-7D2D-4932-8093-42E6D22EFBD0"},"AnimationType":"masterSound","is_imported":false,"isEnabled":true}]},"triggers":[{"@class":"CollisionTrigger","id":{"uuid":"28B5AC1B-9814-483D-B827-6217F2C367EA"},"ownerScriptId":{"uuid":"826065EA-65EF-42E1-92C1-970D5875D346"},"logicOperation":0,"resultType":0,"isInverted":false,"eventType":"in","targetBindingLink":{"@class":"BindingLink","targetId":{"uuid":"2ECB3BA4-F2F4-42DD-86E8-322283040C6C"}},"zoneBindingLink":{"@class":"BindingLink","targetId":{"uuid":"EFF14DB0-66B7-48CC-8B63-D88EA44E8F23"}},"allowed":false}]}