{"@class":"TimeLineScript","id":{"uuid":"926D29FC-2AF0-41FA-988C-3BCEFB9926B7"},"name":"Animation","enableOnAwake":false,"loop":true,"jumpToFirstFrameAtEnd":false,"speed":1.0,"weight":1.0,"loopStartTime":0,"loopDuration":0,"is_imported":false,"type":"user","scripts":{"@class":"StdListRuntimeScript","list":[{"@class":"AnimationScript","id":{"uuid":"174763F4-7213-4A7C-BD64-E06CE49A0AE3"},"name":"rays_mesh","enableOnAwake":false,"OwnerLink":{"@class":"BindingLink","targetId":{"uuid":"91EE69D5-645E-40A2-9B8C-CBAB4778706E"},"targetRelativeAddress":{"@class":"NodeRelativeAddressBase","index":7,"name":"Rays","subaddress":{"@class":"NodeRelativeAddressBase","index":0,"name":"rays_mesh"}}},"animation":{"uuid":"2521657F-C1B4-4A18-94D7-EABC9F9EFA8F"},"AnimationType":"object3D","is_imported":false,"isEnabled":true},{"@class":"AnimationScript","id":{"uuid":"94F2D495-47F0-4D02-90E9-961BCE0F1CC5"},"name":"rays_mesh 2","enableOnAwake":false,"OwnerLink":{"@class":"BindingLink","targetId":{"uuid":"A15E5B7A-CE0F-4C5C-B569-9A316C79BDC1"},"targetRelativeAddress":{"@class":"NodeRelativeAddressBase","index":7,"name":"Rays","subaddress":{"@class":"NodeRelativeAddressBase","index":1,"name":"rays_mesh 2"}}},"animation":{"uuid":"39C49CE5-9C67-42FB-BC6F-D2E9540377F0"},"AnimationType":"object3D","is_imported":false,"isEnabled":true},{"@class":"AnimationScript","id":{"uuid":"C5FB5636-374F-47C9-BB2A-436D9270679B"},"name":"Rays Appearance","enableOnAwake":false,"OwnerLink":{"@class":"BindingLink","targetId":{"uuid":"D70058B2-68E7-4F6B-B6EE-2AF3F6CA1D1A"},"targetRelativeAddress":{"@class":"NodeRelativeAddressBase","index":0,"name":"Rays","subaddress":{"@class":"NodeRelativeAddressBase","index":2,"name":"Rays Appearance"}}},"animation":{"uuid":"9396F69A-7DF9-4BE8-B5AF-0DFA83BB1F5C"},"AnimationType":"object3D","is_imported":false,"isEnabled":true}]},"triggers":[{"@class":"AnimationTrigger","id":{"uuid":"CAE3EB86-BCE3-4835-BA44-234E37D73464"},"ownerScriptId":{"uuid":"926D29FC-2AF0-41FA-988C-3BCEFB9926B7"},"logicOperation":0,"resultType":0,"isInverted":false,"event":2,"bindingLink":{"@class":"BindingLink","targetId":{"uuid":"D70058B2-68E7-4F6B-B6EE-2AF3F6CA1D1A"}}},{"@class":"CollisionTrigger","id":{"uuid":"AD820AD4-82CE-41AE-947A-6C1DD5AC3937"},"ownerScriptId":{"uuid":"926D29FC-2AF0-41FA-988C-3BCEFB9926B7"},"logicOperation":1,"resultType":3,"isInverted":false,"eventType":"inside","targetBindingLink":{"@class":"BindingLink","targetId":{"uuid":"70AEE207-0F50-4896-B837-578FDA405069"}},"zoneBindingLink":{"@class":"BindingLink","targetId":{"uuid":"D8F05A03-0158-4E53-9354-4DDA69E50FF3"}},"allowed":false},{"@class":"AnimationTrigger","id":{"uuid":"198E4DF5-D981-4F17-87EB-D65DD910C1B1"},"ownerScriptId":{"uuid":"926D29FC-2AF0-41FA-988C-3BCEFB9926B7"},"logicOperation":1,"resultType":0,"isInverted":false,"event":3,"bindingLink":{"@class":"BindingLink","targetId":{"uuid":"2DF3332E-A260-47EF-8DC8-54380A580F82"}}}]}